soccer_info/__init__.py
soccer_info/py.typed
soccer_info/client/__init__.py
soccer_info/client/base_client.py
soccer_info/client/async_/__init__.py
soccer_info/client/async_/async_client.py
soccer_info/client/async_/async_httpclient.py
soccer_info/client/async_/domain/__init__.py
soccer_info/client/async_/domain/championships.py
soccer_info/client/async_/domain/countries.py
soccer_info/client/async_/domain/matches.py
soccer_info/client/common/__init__.py
soccer_info/client/common/domain/__init__.py
soccer_info/client/common/domain/championships.py
soccer_info/client/common/domain/countries.py
soccer_info/client/common/domain/matches.py
soccer_info/client/sync/__init__.py
soccer_info/client/sync/client.py
soccer_info/client/sync/httpclient.py
soccer_info/client/sync/domain/__init__.py
soccer_info/client/sync/domain/championships.py
soccer_info/client/sync/domain/countries.py
soccer_info/client/sync/domain/matches.py
soccer_info/requests_/__init__.py
soccer_info/requests_/headers.py
soccer_info/requests_/parameters.py
soccer_info/responses/__init__.py
soccer_info/responses/base.py
soccer_info/responses/championships/__init__.py
soccer_info/responses/championships/models.py
soccer_info/responses/countries/__init__.py
soccer_info/responses/countries/models.py
soccer_info/responses/matches/__init__.py
soccer_info/responses/matches/models.py
soccer_info/settings/__init__.py
soccer_info/settings/builder.py
soccer_info/settings/settings.py
soccer_info-0.2.1.dist-info/licenses/LICENSE
soccer_info-0.2.1.dist-info/METADATA
soccer_info-0.2.1.dist-info/WHEEL
soccer_info-0.2.1.dist-info/top_level.txt
soccer_info-0.2.1.dist-info/RECORD
