Metadata-Version: 2.4
Name: soccer-info
Version: 0.2.1
Summary: Python SDK for Soccer Football Info API via RapidAPI
Author-email: Ilay Arlev <eliyahu.arlev@gmail.com>
Maintainer-email: Ilay Arlev <eliyahu.arlev@gmail.com>
License: MIT
Project-URL: Homepage, https://github.com/eliyahuA/soccer-info
Project-URL: Repository, https://github.com/eliyahuA/soccer-info
Project-URL: Documentation, https://github.com/eliyahuA/soccer-info#readme
Project-URL: Issues, https://github.com/eliyahuA/soccer-info/issues
Project-URL: Changelog, https://github.com/eliyahuA/soccer-info/releases
Keywords: soccer,football,api,rapidapi,sports,sdk,championship,league,sports-data,soccer-api
Classifier: Development Status :: 3 - Alpha
Classifier: Intended Audience :: Developers
Classifier: License :: OSI Approved :: MIT License
Classifier: Programming Language :: Python :: 3
Classifier: Programming Language :: Python :: 3.13
Classifier: Programming Language :: Python :: 3 :: Only
Classifier: Topic :: Software Development :: Libraries :: Python Modules
Classifier: Topic :: Internet :: WWW/HTTP :: Dynamic Content
Classifier: Topic :: Games/Entertainment
Classifier: Operating System :: OS Independent
Classifier: Natural Language :: English
Classifier: Typing :: Typed
Requires-Python: >=3.13
License-File: LICENSE
Requires-Dist: httpx>=0.25.0
Requires-Dist: pydantic>=2.0.0
Provides-Extra: dev
Requires-Dist: pytest>=7.0.0; extra == "dev"
Requires-Dist: pytest-asyncio>=0.21.0; extra == "dev"
Dynamic: license-file
